hackblitz/__init__.py
hackblitz/clients/__init__.py
hackblitz/clients/ingress/__init__.py
hackblitz/clients/ingress/utils.py
hackblitz/clients/ingress/validators.py
hackblitz-0.1.0.dist-info/WHEEL
hackblitz-0.1.0.dist-info/METADATA
hackblitz-0.1.0.dist-info/RECORD
