Metadata-Version: 2.1
Name: hackblitz
Version: 0.1.0
Summary: HackBlitz SDK
Author: Satheesh Kumar
Author-email: mail@satheesh.dev
Requires-Python: >=3.6,<4.0
Classifier: Programming Language :: Python :: 3
Classifier: Programming Language :: Python :: 3.10
Classifier: Programming Language :: Python :: 3.6
Classifier: Programming Language :: Python :: 3.7
Classifier: Programming Language :: Python :: 3.8
Classifier: Programming Language :: Python :: 3.9
